{
  "main": {
    "id": "17d7a5216cd24ae3",
    "type": "split",
    "children": [
      {
        "id": "15f0390215d3b1fb",
        "type": "tabs",
        "dimension": 36.87168279737746,
        "children": [
          {
            "id": "d60ade257997ab51",
            "type": "leaf",
            "state": {
              "type": "pdf",
              "state": {
                "file": "00.References/Discrete_Theory_All.pdf"
              }
            }
          },
          {
            "id": "8b46b5ded68afc01",
            "type": "leaf",
            "state": {
              "type": "pdf",
              "state": {
                "file": "00.References/Discreta_Exercises_All_Solved.pdf"
              }
            }
          }
        ],
        "currentTab": 1
      },
      {
        "id": "ef4fd921a45b13fc",
        "type": "tabs",
        "dimension": 31.75148298470184,
        "children": [
          {
            "id": "01b928e07da67059",
            "type": "leaf",
            "state": {
              "type": "pdf",
              "state": {
                "file": "00.References/Discreta_Exercises_All_Solved.pdf"
              }
            }
          }
        ]
      },
      {
        "id": "9af070794635d90b",
        "type": "tabs",
        "dimension": 31.376834217920702,
        "children": [
          {
            "id": "367f7b7197f7cb79",
            "type": "leaf",
            "state": {
              "type": "markdown",
              "state": {
                "file": "02 - Atomic/20240519 - 164454 - Exercises - Order relations.md",
                "mode": "source",
                "backlinks": true,
                "source": false
              }
            }
          },
          {
            "id": "aa6f0fd2c1599c60",
            "type": "leaf",
            "state": {
              "type": "markdown",
              "state": {
                "file": "02 - Atomic/20240519 - 165004 - Order Relation.md",
                "mode": "source",
                "backlinks": true,
                "source": false
              }
            }
          },
          {
            "id": "7613166763cbe9e4",
            "type": "leaf",
            "state": {
              "type": "markdown",
              "state": {
                "file": "02 - Atomic/20240519 - 172247 - Algorithm - Topological sort.md",
                "mode": "source",
                "backlinks": true,
                "source": false
              }
            }
          },
          {
            "id": "d6b277baa8a8fefa",
            "type": "leaf",
            "state": {
              "type": "markdown",
              "state": {
                "file": "02 - Atomic/20240519 - 172613 - Well-ordered set.md",
                "mode": "source",
                "backlinks": true,
                "source": false
              }
            }
          }
        ]
      }
    ],
    "direction": "vertical"
  },
  "left": {
    "id": "145a221e0e2d66f9",
    "type": "split",
    "children": [
      {
        "id": "499a66215ecf4828",
        "type": "tabs",
        "children": [
          {
            "id": "b89f836cb1d8a8cd",
            "type": "leaf",
            "state": {
              "type": "file-explorer",
              "state": {
                "sortOrder": "alphabetical"
              }
            }
          },
          {
            "id": "fb67b24a9341e2ad",
            "type": "leaf",
            "state": {
              "type": "search",
              "state": {
                "query": "",
                "matchingCase": false,
                "explainSearch": false,
                "collapseAll": false,
                "extraContext": false,
                "sortOrder": "alphabetical"
              }
            }
          },
          {
            "id": "11873d04252143b6",
            "type": "leaf",
            "state": {
              "type": "bookmarks",
              "state": {}
            }
          }
        ]
      },
      {
        "id": "74476affe76ac5b2",
        "type": "tabs",
        "children": [
          {
            "id": "0b81a69190cd8ecc",
            "type": "leaf",
            "state": {
              "type": "calendar",
              "state": {}
            }
          }
        ]
      }
    ],
    "direction": "horizontal",
    "width": 357.00418853759766,
    "collapsed": true
  },
  "right": {
    "id": "8881aa8c79e29157",
    "type": "split",
    "children": [
      {
        "id": "5997a5c0c99a8696",
        "type": "tabs",
        "children": [
          {
            "id": "6ac2d010ad26804a",
            "type": "leaf",
            "state": {
              "type": "backlink",
              "state": {
                "file": "02 - Atomic/20240519 - 164454 - Exercises - Order relations.md",
                "collapseAll": false,
                "extraContext": false,
                "sortOrder": "alphabetical",
                "showSearch": false,
                "searchQuery": "",
                "backlinkCollapsed": false,
                "unlinkedCollapsed": true
              }
            }
          },
          {
            "id": "19bec87b90240b33",
            "type": "leaf",
            "state": {
              "type": "outgoing-link",
              "state": {
                "file": "02 - Atomic/20240519 - 164454 - Exercises - Order relations.md",
                "linksCollapsed": false,
                "unlinkedCollapsed": true
              }
            }
          },
          {
            "id": "4d9e8083eba3a4a2",
            "type": "leaf",
            "state": {
              "type": "tag",
              "state": {
                "sortOrder": "frequency",
                "useHierarchy": true
              }
            }
          },
          {
            "id": "fea6a7bd9cb3093d",
            "type": "leaf",
            "state": {
              "type": "review-queue-list-view",
              "state": {}
            }
          }
        ],
        "currentTab": 3
      },
      {
        "id": "f97aefa6b972e655",
        "type": "tabs",
        "children": [
          {
            "id": "36d1a43796975b90",
            "type": "leaf",
            "state": {
              "type": "localgraph",
              "state": {
                "file": "02 - Atomic/20240519 - 164454 - Exercises - Order relations.md",
                "options": {
                  "collapse-filter": false,
                  "search": "",
                  "localJumps": 2,
                  "localBacklinks": true,
                  "localForelinks": true,
                  "localInterlinks": false,
                  "showTags": false,
                  "showAttachments": true,
                  "hideUnresolved": false,
                  "collapse-color-groups": true,
                  "colorGroups": [],
                  "collapse-display": false,
                  "showArrow": false,
                  "textFadeMultiplier": 0,
                  "nodeSizeMultiplier": 1,
                  "lineSizeMultiplier": 1,
                  "collapse-forces": false,
                  "centerStrength": 0,
                  "repelStrength": 17.3531310522918,
                  "linkStrength": 0.595351839896708,
                  "linkDistance": 374,
                  "scale": 0.11168871508752963,
                  "close": true
                }
              }
            }
          }
        ]
      },
      {
        "id": "2758c03c7f8ca0ae",
        "type": "tabs",
        "children": [
          {
            "id": "1223c0f85c541969",
            "type": "leaf",
            "state": {
              "type": "outline",
              "state": {
                "file": "02 - Atomic/20240519 - 164454 - Exercises - Order relations.md"
              }
            }
          }
        ]
      }
    ],
    "direction": "horizontal",
    "width": 741,
    "collapsed": true
  },
  "left-ribbon": {
    "hiddenItems": {
      "homepage:Open homepage": true,
      "obsidian-importer:Open Importer": true,
      "zk-prefixer:Create new unique note": true,
      "switcher:Open quick switcher": true,
      "canvas:Create new canvas": true,
      "daily-notes:Open today's daily note": true,
      "templates:Insert template": true,
      "command-palette:Open command palette": true,
      "obsidian-spaced-repetition:Review flashcards": true,
      "templater-obsidian:Templater": true,
      "omnisearch:Omnisearch": false,
      "graph:Open graph view": false,
      "workspaces:Manage workspace layouts": false
    }
  },
  "active": "367f7b7197f7cb79",
  "lastOpenFiles": [
    "00.References/Discreta_Exercises_All_Solved.pdf",
    "02 - Atomic/20240519 - 164454 - Exercises - Order relations.md",
    "02 - Atomic/20240519 - 165004 - Order Relation.md",
    "02 - Atomic/20240519 - 182434 -.md",
    "00.References/Discrete_Theory_All.pdf",
    "02 - Atomic/20240510 - 090701 - Exercises - Equivalence relations.md",
    "02 - Atomic/Binary Relations.md",
    "02 - Atomic/20240519 - 172247 - Algorithm - Topological sort.md",
    "02 - Atomic/20240519 - 172613 - Well-ordered set.md",
    "99 - Meta/0. Attachments/Screenshot 2024-05-19 at 17.25.21.png",
    "02 - Atomic/20240519 - 165637 - Hasse diagram.md",
    "99 - Meta/0. Attachments/Screenshot 2024-05-19 at 16.59.49.png",
    "01.Areas/1.UC3M/Discrete Math.md",
    "01.Areas/0.DailyNote/2024-05-19.md",
    "02 - Atomic/20240517 - 163856 - Files.md",
    "02 - Atomic/Pascal's triangle.md",
    "02 - Atomic/20240415 - 114153 - Inverse of a binary relation.md",
    "02 - Atomic/Concurrency.md",
    "02 - Atomic/Race condition.md",
    "02 - Atomic/Mutual exclusion.md",
    "02 - Atomic/20240515 - 011944 - Ordered subsets.md",
    "02 - Atomic/20240515 - 013650 - Principle - Inclusion-exclusion principle.md",
    "02 - Atomic/20240515 - 023210 - Theorem - The handshaking theorem.md",
    "02 - Atomic/20240418 - 194138 - The Heat Conduction Equation.md",
    "02 - Atomic/20240515 - 013001 - Theorem - Newton's binomial theorem.md",
    "02 - Atomic/20240423 - 131817 - Chromatic poly of a wheel graph.md",
    "00.References/OS_Biblio_J.Carretero.pdf",
    "01.Areas/1.UC3M/Operating Systems.md",
    "02 - Atomic/SoftwareDev_Theory_Ch 0_Intro.md",
    "01.Areas/1.UC3M/Software Dev.md",
    "00.References/OS_Biblio_OpSystemConcepts.pdf",
    "00.References/DiffCalc_Theory_EcuacionDeCalor.pdf",
    "99 - Meta/0. Attachments/Pasted image 20240515040900.png",
    "99 - Meta/0. Attachments/Pasted image 20240515033016.png",
    "99 - Meta/0. Attachments/Screenshot 2024-05-15 at 03.29.37.png",
    "00.References/Logic_Resource_Theorems and Derived Rules Combined.pdf",
    "00.References/OS_Theory_Concurrent-Servers.pdf",
    "00.References/SoftwareDev_PracticeTheorySession 08.pdf",
    "99 - Meta/0. Attachments/Screenshot 2024-05-08 at 12.44.50.png",
    "99 - Meta/0. Attachments/Screenshot 2024-05-08 at 12.43.42.png",
    "99 - Meta/0. Attachments/Screenshot 2024-05-08 at 12.39.50.png",
    "99 - Meta/0. Attachments/Screenshot 2024-05-08 at 11.34.11.png",
    "99 - Meta/0. Attachments/Screenshot 2024-05-08 at 11.30.16.png",
    "00.References/Calc_Theory_All.pdf",
    "00.References/DiffCalc_Theory_EquacioónDeOnda.pdf",
    "01.Areas/3.Matterhorn/Tatto.canvas",
    "01.Areas/1.UC3M/Movilidad.canvas",
    "01.Areas/1.UC3M/Files and data bases.canvas",
    "01.Areas/1.UC3M/Discrete Math.canvas",
    "01.Areas/1.UC3M/Operating Systems.canvas",
    "01.Areas/1.UC3M/Software Dev.canvas",
    "01.Areas/1.UC3M/Logic.canvas",
    "01.Areas/1.UC3M/Diff Calculus.canvas",
    "01.Areas/2.TIto/HTB_Linux Fundamentals.canvas"
  ]
}